tudu/__init__.py
tudu/cli.py
tudu/data_controllers.py
tudu/exception.py
tudu/model.py
tudu/startup.py
tudu/util.py
tudu/tui/__init__.py
tudu/tui/help.py
tudu/tui/prompt.py
tudu/tui/task.py
tudu/tui/tui.py
tudu/tui/ui.py
tudu-0.2.dist-info/METADATA
tudu-0.2.dist-info/WHEEL
tudu-0.2.dist-info/entry_points.txt
tudu-0.2.dist-info/top_level.txt
tudu-0.2.dist-info/RECORD
