Metadata-Version: 2.1
Name: tudu
Version: 0.2
Summary: simple command line tool with a tui mode for managing your to-do lists
Home-page: https://github.com/lubczanska/tudu
Author: lubczanska
License: UNKNOWN
Platform: UNKNOWN
Classifier: Programming Language :: Python :: 3
Classifier: Programming Language :: Python :: 3.7
Classifier: License :: OSI Approved :: MIT License
Classifier: Environment :: Console
Classifier: Environment :: Console :: Curses
Requires-Python: >=3.6
Requires-Dist: plyer (>=2.0.0)
Requires-Dist: SQLAlchemy (>=1.4.30)
